raglib/__init__.py
raglib/chunking/__init__.py
raglib/chunking/smart_chunker.py
raglib/embeddings/__init__.py
raglib/embeddings/gemini.py
raglib/embeddings/huggingface.py
raglib/embeddings/openai.py
raglib/vector_stores/__init__.py
raglib/vector_stores/faiss_store.py
raglib/vector_stores/qdrant_store.py
raggenius-0.2.1.dist-info/METADATA
raggenius-0.2.1.dist-info/WHEEL
raggenius-0.2.1.dist-info/entry_points.txt
raggenius-0.2.1.dist-info/top_level.txt
raggenius-0.2.1.dist-info/RECORD
