Metadata-Version: 2.4
Name: raggenius
Version: 0.2.1
Summary: A modular RAG library with embeddings and vector store support
Author: Abhishek Ghotekar
Author-email: Abhishek Ghotekar <your.email@example.com>
License: MIT
Requires-Python: >=3.7
Requires-Dist: sentence-transformers>=2.2.2
Requires-Dist: qdrant-client>=1.3.0
Requires-Dist: faiss-cpu; sys_platform != "win32"
Requires-Dist: openai>=1.0.0
Requires-Dist: google-generativeai>=0.3.1
Requires-Dist: pyyaml>=6.0
Dynamic: author
Dynamic: requires-python
